LICENSE.TXT
README.md
setup.py
linear_reg_youcef/__init__.py
linear_reg_youcef/linear_reg_youcef.py
linear_reg_youcef.egg-info/PKG-INFO
linear_reg_youcef.egg-info/SOURCES.txt
linear_reg_youcef.egg-info/dependency_links.txt
linear_reg_youcef.egg-info/top_level.txt