Metadata-Version: 2.1
Name: linear_reg_youcef
Version: 1.0.0
Summary: `linear_reg_youcef` is a Python library for predicting values based on linear regression concept
Home-page: http://pypi.python.org/pypi/linear_reg_youcef/
Author: talbi_youcef
Author-email: y.talbi@esi-sba.dz
License: LICENSE.txt
License-File: LICENSE.TXT
